build/lib/build/lib/build/lib/build/lib/build/lib/kintsugi/utils.py
build/lib/build/lib/build/lib/build/lib/kintsugi/utils.py
build/lib/build/lib/build/lib/build/lib/kintsugi/secureserialization/serializer.py
build/lib/build/lib/build/lib/kintsugi/utils.py
build/lib/build/lib/build/lib/kintsugi/secureserialization/serializer.py
build/lib/build/lib/kintsugi/utils.py
build/lib/build/lib/kintsugi/secureserialization/serializer.py
build/lib/kintsugi/utils.py
build/lib/kintsugi/secureserialization/serializer.py
kintsugi/utils.py
kintsugi/secureserialization/serializer.py
ripple_kintsugi-0.0.1.dist-info/METADATA
ripple_kintsugi-0.0.1.dist-info/WHEEL
ripple_kintsugi-0.0.1.dist-info/top_level.txt
ripple_kintsugi-0.0.1.dist-info/RECORD
