Metadata-Version: 2.1
Name: ripple-kintsugi
Version: 0.0.1
Summary: Ripple's Kintsugi Library for Machine Learning Standardization.
Home-page: https://github.com/mlflow/mlflow-export-import
Author: Ripple Megatron Devs
Requires-Python: >=3
Requires-Dist: loguru (==0.5.3)
